{"total_count": 257, "states": [{"name": "Andaman and Nicobar Islands", "count": 0, "centers": []}, {"name": "Andhra Pradesh", "count": 0, "centers": []}, {"name": "Arunachal Pradesh", "count": 0, "centers": []}, {"name": "Assam", "count": 0, "centers": []}, {"name": "Bihar", "count": 0, "centers": []}, {"name": "Chandigarh", "count": 0, "centers": []}, {"name": "Chhattisgarh", "count": 2, "centers": [{"name": "Chc Kasdol", "district": "Baloda bazar", "state": "Chhattisgarh", "pincode": 493335, "available": 3}, {"name": "CHC Chhura 18", "district": "Gariaband", "state": "Chhattisgarh", "pincode": 493996, "available": 26}]}, {"name": "Dadra and Nagar Haveli", "count": 0, "centers": []}, {"name": "Daman and Diu", "count": 0, "centers": []}, {"name": "Delhi", "count": 113, "centers": [{"name": "SBV Rani Jhansi Road SITE 4", "district": "Central Delhi", "state": "Delhi", "pincode": 110055, "available": 208}, {"name": "SBV JAMA MASJID HINDI SITE 5", "district": "Central Delhi", "state": "Delhi", "pincode": 110006, "available": 375}, {"name": "Sarvodhya V Mori G NO.1 SITE 3", "district": "Central Delhi", "state": "Delhi", "pincode": 110006, "available": 197}, {"name": "VBGSSS NPL COLONY SITE 2", "district": "Central Delhi", "state": "Delhi", "pincode": 110060, "available": 1}, {"name": "VBGSSS NPL COLONY SITE 4", "district": "Central Delhi", "state": "Delhi", "pincode": 110060, "available": 125}, {"name": "Sarvodhya V Mori G NO.1 SITE 4", "district": "Central Delhi", "state": "Delhi", "pincode": 110006, "available": 141}, {"name": "SBV Rani Jhansi Road SITE 2", "district": "Central Delhi", "state": "Delhi", "pincode": 110055, "available": 55}, {"name": "VBGSSS NPL COLONY SITE 3", "district": "Central Delhi", "state": "Delhi", "pincode": 110060, "available": 6}, {"name": "SBV JAMA MASJID URDU SITE 1", "district": "Central Delhi", "state": "Delhi", "pincode": 110006, "available": 309}, {"name": "Sarvodhya V Mori G NO.1 SITE 5", "district": "Central Delhi", "state": "Delhi", "pincode": 110006, "available": 359}, {"name": "SBV JAMA MASJID URDU SITE 2", "district": "Central Delhi", "state": "Delhi", "pincode": 110006, "available": 429}, {"name": "SBV Rani Jhansi Road SITE 3", "district": "Central Delhi", "state": "Delhi", "pincode": 110055, "available": 181}, {"name": "Dr B L Kapur Hospital Site 4", "district": "Central Delhi", "state": "Delhi", "pincode": 110005, "available": 1}, {"name": "Sarvodhya V Mori G NO.1 SITE 2", "district": "Central Delhi", "state": "Delhi", "pincode": 110006, "available": 1144}, {"name": "SBV Rani Jhansi Road SITE 5", "district": "Central Delhi", "state": "Delhi", "pincode": 110055, "available": 195}, {"name": "SBV JAMA MASJID URDU SITE 3", "district": "Central Delhi", "state": "Delhi", "pincode": 110006, "available": 425}, {"name": "SBV JAMA MASJID HINDI SITE 4", "district": "Central Delhi", "state": "Delhi", "pincode": 110006, "available": 326}, {"name": "Sarvodhya V Mori G NO.1 SITE 1", "district": "Central Delhi", "state": "Delhi", "pincode": 110006, "available": 1}, {"name": "VBGSSS NPL COLONY SITE 5", "district": "Central Delhi", "state": "Delhi", "pincode": 110060, "available": 169}, {"name": "Atal Adarsh Vidyalaya Site 1.", "district": "New Delhi", "state": "Delhi", "pincode": 110021, "available": 1}, {"name": "Atal Adarsh Vidyalaya Site 2.", "district": "New Delhi", "state": "Delhi", "pincode": 110021, "available": 1}, {"name": "Gov.Girls S.Sec.Sch.No.1 Site4", "district": "North Delhi", "state": "Delhi", "pincode": 110039, "available": 404}, {"name": "Govt. Girl Senior Sec.School 2", "district": "North Delhi", "state": "Delhi", "pincode": 110042, "available": 2}, {"name": "Sarvodaya Bal Vidyalaya 5", "district": "North Delhi", "state": "Delhi", "pincode": 110039, "available": 423}, {"name": "Govt.Girls SeniorSec. School5", "district": "North Delhi", "state": "Delhi", "pincode": 110042, "available": 350}, {"name": "Sarvodaya Bal Vidyalaya 4", "district": "North Delhi", "state": "Delhi", "pincode": 110039, "available": 437}, {"name": "SKV A Block Jahangirpuri", "district": "North Delhi", "state": "Delhi", "pincode": 110033, "available": 41}, {"name": "Gov.Girls S.Sec.Sch.No.1 Site2", "district": "North Delhi", "state": "Delhi", "pincode": 110039, "available": 111}, {"name": "Gov.Girls S.Sec.Sch.No.1 Site3", "district": "North Delhi", "state": "Delhi", "pincode": 110039, "available": 396}, {"name": "Govt.Girl Senior Sec. School 3", "district": "North Delhi", "state": "Delhi", "pincode": 110042, "available": 233}, {"name": "GBSS School Jahangirpuri 4", "district": "North Delhi", "state": "Delhi", "pincode": 110033, "available": 267}, {"name": "GBSS School Jahangirpuri 5", "district": "North Delhi", "state": "Delhi", "pincode": 110033, "available": 351}, {"name": "SKV A Block Jahangirpuri 4", "district": "North Delhi", "state": "Delhi", "pincode": 110033, "available": 344}, {"name": "SKV A Block Jahangirpuri 5", "district": "North Delhi", "state": "Delhi", "pincode": 110033, "available": 1}, {"name": "SKV A Block Jahangirpuri 2", "district": "North Delhi", "state": "Delhi", "pincode": 110033, "available": 97}, {"name": "Gov.Girls S.Sec.Sch.No.1 Site5", "district": "North Delhi", "state": "Delhi", "pincode": 110039, "available": 395}, {"name": "Sarvodaya Bal Vidyalaya 1", "district": "North Delhi", "state": "Delhi", "pincode": 110039, "available": 270}, {"name": "Sarvodaya Bal Vidyalaya 3", "district": "North Delhi", "state": "Delhi", "pincode": 110039, "available": 434}, {"name": "GBSS School Jahangirpuri 1", "district": "North Delhi", "state": "Delhi", "pincode": 110033, "available": 1}, {"name": "Govt.Girls SeniorSec. School4", "district": "North Delhi", "state": "Delhi", "pincode": 110042, "available": 344}, {"name": "Sarvodaya Bal Vidyalaya 2", "district": "North Delhi", "state": "Delhi", "pincode": 110039, "available": 413}, {"name": "Gov.Girls S.Sec.Sch.No.1 Site1", "district": "North Delhi", "state": "Delhi", "pincode": 110039, "available": 18}, {"name": "GBSS School Jahangirpuri 3", "district": "North Delhi", "state": "Delhi", "pincode": 110033, "available": 119}, {"name": "SKV A Block Jahangirpuri 3", "district": "North Delhi", "state": "Delhi", "pincode": 110033, "available": 338}, {"name": "Gov Boys Sec School Site-2", "district": "North East Delhi", "state": "Delhi", "pincode": 110094, "available": 62}, {"name": "Gov Boys Sec School Site-4", "district": "North East Delhi", "state": "Delhi", "pincode": 110094, "available": 390}, {"name": "Gov Girls S Sec School Site-2", "district": "North East Delhi", "state": "Delhi", "pincode": 110094, "available": 383}, {"name": "Gov Girls Sr Sec School Site-2", "district": "North East Delhi", "state": "Delhi", "pincode": 110094, "available": 430}, {"name": "Gov Boys Sr Se Sc No. 1 Site-5", "district": "North East Delhi", "state": "Delhi", "pincode": 110053, "available": 400}, {"name": "Gov Girls S Sec School Site-5", "district": "North East Delhi", "state": "Delhi", "pincode": 110094, "available": 431}, {"name": "Gov Girls S Sec School Site-3", "district": "North East Delhi", "state": "Delhi", "pincode": 110094, "available": 425}, {"name": "Gov Girls Sr Se Sc No.1 Site-1", "district": "North East Delhi", "state": "Delhi", "pincode": 110053, "available": 49}, {"name": "Gov Boys Sr Sec School Site-5", "district": "North East Delhi", "state": "Delhi", "pincode": 110094, "available": 398}, {"name": "Gov Girls Sr Sec School Site-5", "district": "North East Delhi", "state": "Delhi", "pincode": 110094, "available": 419}, {"name": "Gov Girls Sr Sec School Site-1", "district": "North East Delhi", "state": "Delhi", "pincode": 110094, "available": 365}, {"name": "Gov Boys Sr Sec School Site-3", "district": "North East Delhi", "state": "Delhi", "pincode": 110094, "available": 380}, {"name": "Gov Boys Sec School Site-5", "district": "North East Delhi", "state": "Delhi", "pincode": 110094, "available": 417}, {"name": "Gov Boys Sr Sec School Site-1", "district": "North East Delhi", "state": "Delhi", "pincode": 110094, "available": 235}, {"name": "Gov Boys Sr Se Sc No. 1 Site-4", "district": "North East Delhi", "state": "Delhi", "pincode": 110053, "available": 367}, {"name": "Gov Girls Sr Se Sc No.1 Site-3", "district": "North East Delhi", "state": "Delhi", "pincode": 110053, "available": 387}, {"name": "Gov Girls Sr Sec School Site-4", "district": "North East Delhi", "state": "Delhi", "pincode": 110094, "available": 426}, {"name": "Gov Girls S Sec School Site-4", "district": "North East Delhi", "state": "Delhi", "pincode": 110094, "available": 426}, {"name": "Gov Girls Sr Se Sc No.1 Site-2", "district": "North East Delhi", "state": "Delhi", "pincode": 110053, "available": 377}, {"name": "Gov Girls S Sec School Site-1", "district": "North East Delhi", "state": "Delhi", "pincode": 110094, "available": 348}, {"name": "Gov Girls Sr Sec School Site-3", "district": "North East Delhi", "state": "Delhi", "pincode": 110094, "available": 308}, {"name": "Gov Boys Sr Se Sc No. 1 Site-1", "district": "North East Delhi", "state": "Delhi", "pincode": 110053, "available": 43}, {"name": "Gov Boys Sr Se Sc No. 1 Site-3", "district": "North East Delhi", "state": "Delhi", "pincode": 110053, "available": 262}, {"name": "Gov Girls Sr Se Sc No.1 Site-4", "district": "North East Delhi", "state": "Delhi", "pincode": 110053, "available": 429}, {"name": "Gov Boys Sec School Site-3", "district": "North East Delhi", "state": "Delhi", "pincode": 110094, "available": 238}, {"name": "Gov Boys Sr Sec School Site-4", "district": "North East Delhi", "state": "Delhi", "pincode": 110094, "available": 428}, {"name": "Gov Girls Sr Se Sc No.1 Site-5", "district": "North East Delhi", "state": "Delhi", "pincode": 110053, "available": 399}, {"name": "Gov Boys Sr Se Sc No. 1 Site-2", "district": "North East Delhi", "state": "Delhi", "pincode": 110053, "available": 214}, {"name": "Gov Boys Sr Sec School Site-2", "district": "North East Delhi", "state": "Delhi", "pincode": 110094, "available": 401}, {"name": "SARVODAY VIDYALAY POOTHKALAN 2", "district": "North West Delhi", "state": "Delhi", "pincode": 110086, "available": 1}, {"name": "SKV KARALA SCHOOL Site 4", "district": "North West Delhi", "state": "Delhi", "pincode": 110081, "available": 200}, {"name": "GOVT. SARVODAYA B.V. Site 5", "district": "North West Delhi", "state": "Delhi", "pincode": 110086, "available": 2}, {"name": "SKV KARALA SCHOOL Site 5", "district": "North West Delhi", "state": "Delhi", "pincode": 110081, "available": 243}, {"name": "GBSSS Saboli Extn Site 5", "district": "Shahdara", "state": "Delhi", "pincode": 110093, "available": 25}, {"name": "S.KanyaVidyalayaChiragDelhiS.4", "district": "South Delhi", "state": "Delhi", "pincode": 110017, "available": 2}, {"name": "SCHOOL OF EXCE. MPK SITE-1", "district": "South East Delhi", "state": "Delhi", "pincode": 110076, "available": 13}, {"name": "SBV KAUTILYA (1925003) SITE-5", "district": "South East Delhi", "state": "Delhi", "pincode": 110048, "available": 70}, {"name": "GBSSS MOLARBAND SITE-2", "district": "South East Delhi", "state": "Delhi", "pincode": 110044, "available": 1}, {"name": "CO-ED SCHOOL JANGPURA SITE-4", "district": "South East Delhi", "state": "Delhi", "pincode": 110044, "available": 1}, {"name": "SCHOOL OF EXCE. MPK SITE-2", "district": "South East Delhi", "state": "Delhi", "pincode": 110076, "available": 114}, {"name": "SKV/SBV SANGAM VIHAR SITE-2", "district": "South East Delhi", "state": "Delhi", "pincode": 110044, "available": 79}, {"name": "SBV KAUTILYA (1925003) SITE-4", "district": "South East Delhi", "state": "Delhi", "pincode": 110048, "available": 18}, {"name": "SKV/SBV SANGAM VIHAR SITE-1", "district": "South East Delhi", "state": "Delhi", "pincode": 110044, "available": 3}, {"name": "S B V (1516010)", "district": "West Delhi", "state": "Delhi", "pincode": 110015, "available": 29}, {"name": "S B V (1516010) Sites 5", "district": "West Delhi", "state": "Delhi", "pincode": 110015, "available": 297}, {"name": "S.K.V Chand Nagar Sites 2", "district": "West Delhi", "state": "Delhi", "pincode": 110015, "available": 239}, {"name": "GBSSS 1514112 Site 2", "district": "West Delhi", "state": "Delhi", "pincode": 110064, "available": 28}, {"name": "GBSSS 1514112 Site 5", "district": "West Delhi", "state": "Delhi", "pincode": 110064, "available": 155}, {"name": "S.K.V Chand Nagar Site 1", "district": "West Delhi", "state": "Delhi", "pincode": 110015, "available": 65}, {"name": "Govt Boys S.S.S 1617018 Site 1", "district": "West Delhi", "state": "Delhi", "pincode": 110041, "available": 246}, {"name": "S B V (ID 1516143) Sites 2", "district": "West Delhi", "state": "Delhi", "pincode": 110008, "available": 1}, {"name": "GGSSS 1516025 Site 4", "district": "West Delhi", "state": "Delhi", "pincode": 110015, "available": 343}, {"name": "GGSSS 1516025 Site 2", "district": "West Delhi", "state": "Delhi", "pincode": 110015, "available": 184}, {"name": "Govt Boy SSS No.1 (1515010) 2", "district": "West Delhi", "state": "Delhi", "pincode": 110026, "available": 1}, {"name": "S B V (1516010) Sites 4", "district": "West Delhi", "state": "Delhi", "pincode": 110015, "available": 110}, {"name": "GBSSS 1514112 Site 3", "district": "West Delhi", "state": "Delhi", "pincode": 110064, "available": 140}, {"name": "S B V (1516010) Sites 2", "district": "West Delhi", "state": "Delhi", "pincode": 110015, "available": 199}, {"name": "GGSSS 1516025 SIte 1", "district": "West Delhi", "state": "Delhi", "pincode": 110015, "available": 30}, {"name": "Sarvodaya Vidhyala 1516003", "district": "West Delhi", "state": "Delhi", "pincode": 110015, "available": 65}, {"name": "Govt Coed S.S.S 1617214 Site 2", "district": "West Delhi", "state": "Delhi", "pincode": 110041, "available": 250}, {"name": "GGSSS 1516025 Site 3", "district": "West Delhi", "state": "Delhi", "pincode": 110015, "available": 294}, {"name": "Govt Boys S S S 1617018 Site 2", "district": "West Delhi", "state": "Delhi", "pincode": 110041, "available": 158}, {"name": "Govt Coed S.S.S 1617214", "district": "West Delhi", "state": "Delhi", "pincode": 110041, "available": 92}, {"name": "GBSSS 1514112 Site 4", "district": "West Delhi", "state": "Delhi", "pincode": 110064, "available": 177}, {"name": "G.S.B.V (1617002) Site 1", "district": "West Delhi", "state": "Delhi", "pincode": 110041, "available": 1}, {"name": "S B V (1516010) Sites 3", "district": "West Delhi", "state": "Delhi", "pincode": 110015, "available": 251}, {"name": "Govt Coed S.S.S 1617029", "district": "West Delhi", "state": "Delhi", "pincode": 110041, "available": 265}, {"name": "Sarvodya Kanya Vidyala 1516019", "district": "West Delhi", "state": "Delhi", "pincode": 110015, "available": 22}, {"name": "S.K.V Chand Nagar Sites 3", "district": "West Delhi", "state": "Delhi", "pincode": 110015, "available": 220}]}, {"name": "Goa", "count": 0, "centers": []}, {"name": "Gujarat", "count": 7, "centers": [{"name": "Rajpur Hindi 5", "district": "Ahmedabad Corporation", "state": "Gujarat", "pincode": 380021, "available": 1}, {"name": "Urdu Shala No 8", "district": "Ahmedabad Corporation", "state": "Gujarat", "pincode": 380001, "available": 66}, {"name": "ETT BRC Bhavan Ankleshwar", "district": "Bharuch", "state": "Gujarat", "pincode": 393001, "available": 1}, {"name": "Apollo Private Hospital", "district": "Gandhinagar Corporation", "state": "Gujarat", "pincode": 382424, "available": 36}, {"name": "PHC Dholavira 18 To 44", "district": "Kutch", "state": "Gujarat", "pincode": 370165, "available": 10}, {"name": "SADBHAVNA MULTI HOSPITAL", "district": "Surat", "state": "Gujarat", "pincode": 394180, "available": 31}, {"name": "New Life Hospital Sayajipura", "district": "Vadodara", "state": "Gujarat", "pincode": 390019, "available": 56}]}, {"name": "Haryana", "count": 73, "centers": [{"name": "Barara 18-44 CHC", "district": "Ambala", "state": "Haryana", "pincode": 133201, "available": 1}, {"name": "Harodi PHC", "district": "Charkhi Dadri", "state": "Haryana", "pincode": 127308, "available": 2}, {"name": "Santokhpura PHC", "district": "Charkhi Dadri", "state": "Haryana", "pincode": 127022, "available": 13}, {"name": "Government School-1 Gopi", "district": "Charkhi Dadri", "state": "Haryana", "pincode": 127308, "available": 9}, {"name": "PHC Pirthla", "district": "Fatehabad", "state": "Haryana", "pincode": 125120, "available": 2}, {"name": "Meyond Kalan PHC", "district": "Fatehabad", "state": "Haryana", "pincode": 125133, "available": 11}, {"name": "Kullan PHC", "district": "Fatehabad", "state": "Haryana", "pincode": 125106, "available": 18}, {"name": "Civil Hospital Narnaund", "district": "Hisar", "state": "Haryana", "pincode": 125039, "available": 378}, {"name": "SDH Beri 18", "district": "Jhajjar", "state": "Haryana", "pincode": 124201, "available": 1}, {"name": "CHC Pundri", "district": "Kaithal", "state": "Haryana", "pincode": 136026, "available": 40}, {"name": "CHC Kalayat", "district": "Kaithal", "state": "Haryana", "pincode": 136117, "available": 31}, {"name": "CHC Kaul", "district": "Kaithal", "state": "Haryana", "pincode": 136021, "available": 37}, {"name": "PHC Dhand", "district": "Kaithal", "state": "Haryana", "pincode": 136020, "available": 118}, {"name": "PHC Padla", "district": "Kaithal", "state": "Haryana", "pincode": 136027, "available": 131}, {"name": "CHC Siwan", "district": "Kaithal", "state": "Haryana", "pincode": 136033, "available": 45}, {"name": "CHC Rajound", "district": "Kaithal", "state": "Haryana", "pincode": 136044, "available": 87}, {"name": "Sambhali PHC", "district": "Karnal", "state": "Haryana", "pincode": 132157, "available": 1}, {"name": "Parveen Hospital PVT Karnal", "district": "Karnal", "state": "Haryana", "pincode": 132001, "available": 17}, {"name": "Gharaunda CHC", "district": "Karnal", "state": "Haryana", "pincode": 132114, "available": 3}, {"name": "Sehlang CHC", "district": "Mahendragarh", "state": "Haryana", "pincode": 123027, "available": 1}, {"name": "SHKM COLLEGE NALHAR -18", "district": "Nuh", "state": "Haryana", "pincode": 122107, "available": 9}, {"name": "FEROZEPUR JHIRKA CHC - 18", "district": "Nuh", "state": "Haryana", "pincode": 122104, "available": 155}, {"name": "Nuh CHC", "district": "Nuh", "state": "Haryana", "pincode": 122107, "available": 1}, {"name": "CIVIL HOSPITAL MANDIKHERA- 18", "district": "Nuh", "state": "Haryana", "pincode": 122108, "available": 180}, {"name": "PUNHANA CHC- 18", "district": "Nuh", "state": "Haryana", "pincode": 122508, "available": 248}, {"name": "Aayush Disp Sec 9 PKL", "district": "Panchkula", "state": "Haryana", "pincode": 134112, "available": 2}, {"name": "Rair Kalan PHC", "district": "Panipat", "state": "Haryana", "pincode": 132113, "available": 21}, {"name": "Bapoli CHC", "district": "Panipat", "state": "Haryana", "pincode": 132104, "available": 69}, {"name": "Kawi PHC", "district": "Panipat", "state": "Haryana", "pincode": 132113, "available": 24}, {"name": "PHC Basduda", "district": "Rewari", "state": "Haryana", "pincode": 123103, "available": 53}, {"name": "Lakhanmajra 18 Plus", "district": "Rohtak", "state": "Haryana", "pincode": 124514, "available": 77}, {"name": "Dhottar PHC", "district": "Sirsa", "state": "Haryana", "pincode": 125076, "available": 13}, {"name": "Baragudha CHC", "district": "Sirsa", "state": "Haryana", "pincode": 125078, "available": 2}, {"name": "Dadu PHC", "district": "Sirsa", "state": "Haryana", "pincode": 125201, "available": 81}, {"name": "Goriwala PHC", "district": "Sirsa", "state": "Haryana", "pincode": 125103, "available": 2}, {"name": "Jagmalera PHC", "district": "Sirsa", "state": "Haryana", "pincode": 125075, "available": 56}, {"name": "Keharwala PHC", "district": "Sirsa", "state": "Haryana", "pincode": 125103, "available": 1}, {"name": "Mundlana CHC Covishield", "district": "Sonipat", "state": "Haryana", "pincode": 131306, "available": 38}, {"name": "Kundli Phc", "district": "Sonipat", "state": "Haryana", "pincode": 131028, "available": 1}, {"name": "Bhainswal Kalan CHC", "district": "Sonipat", "state": "Haryana", "pincode": 131409, "available": 144}, {"name": "Bidhlan PHC", "district": "Sonipat", "state": "Haryana", "pincode": 131402, "available": 198}, {"name": "Baroda PHC", "district": "Sonipat", "state": "Haryana", "pincode": 131301, "available": 4}, {"name": "Phc Sisana", "district": "Sonipat", "state": "Haryana", "pincode": 131402, "available": 137}, {"name": "PHC Mahra", "district": "Sonipat", "state": "Haryana", "pincode": 131024, "available": 96}, {"name": "Mohana PHC", "district": "Sonipat", "state": "Haryana", "pincode": 131001, "available": 4}, {"name": "Khanda PHC Cowin", "district": "Sonipat", "state": "Haryana", "pincode": 131402, "available": 132}, {"name": "SDH Gohana", "district": "Sonipat", "state": "Haryana", "pincode": 131301, "available": 32}, {"name": "Madina PHC", "district": "Sonipat", "state": "Haryana", "pincode": 131301, "available": 80}, {"name": "Khanpur Kalan PHC", "district": "Sonipat", "state": "Haryana", "pincode": 131305, "available": 176}, {"name": "Moi Majri PHC", "district": "Sonipat", "state": "Haryana", "pincode": 131102, "available": 75}, {"name": "PHC SARAGTHAL", "district": "Sonipat", "state": "Haryana", "pincode": 131305, "available": 94}, {"name": "Farmana PHC Covishield", "district": "Sonipat", "state": "Haryana", "pincode": 131408, "available": 191}, {"name": "Badkhalsha CHC COVISHIELD", "district": "Sonipat", "state": "Haryana", "pincode": 131029, "available": 1}, {"name": "Kharkhoda CHC", "district": "Sonipat", "state": "Haryana", "pincode": 131402, "available": 92}, {"name": "Jagsi PHC Covishield", "district": "Sonipat", "state": "Haryana", "pincode": 131306, "available": 165}, {"name": "Juan CHC", "district": "Sonipat", "state": "Haryana", "pincode": 131024, "available": 213}, {"name": "PHC Ahulana", "district": "Sonipat", "state": "Haryana", "pincode": 131102, "available": 94}, {"name": "Butana PHC", "district": "Sonipat", "state": "Haryana", "pincode": 131302, "available": 46}, {"name": "Purkhash PHC", "district": "Sonipat", "state": "Haryana", "pincode": 131102, "available": 73}, {"name": "Lath PHC", "district": "Sonipat", "state": "Haryana", "pincode": 131301, "available": 109}, {"name": "Rohat PHC", "district": "Sonipat", "state": "Haryana", "pincode": 131402, "available": 1}, {"name": "Dubheta PHC", "district": "Sonipat", "state": "Haryana", "pincode": 131102, "available": 83}, {"name": "Sonipat RHC Covishield", "district": "Sonipat", "state": "Haryana", "pincode": 131001, "available": 1}, {"name": "PHC Shamri", "district": "Sonipat", "state": "Haryana", "pincode": 131306, "available": 165}, {"name": "Rukhi PHC", "district": "Sonipat", "state": "Haryana", "pincode": 131301, "available": 137}, {"name": "Rattuwala Sub Center", "district": "Yamunanagar", "state": "Haryana", "pincode": 133204, "available": 29}, {"name": "Captain Majri", "district": "Yamunanagar", "state": "Haryana", "pincode": 133204, "available": 9}, {"name": "Hangoli Sub Center", "district": "Yamunanagar", "state": "Haryana", "pincode": 133103, "available": 22}, {"name": "DHEEMO SUB CENTER", "district": "Yamunanagar", "state": "Haryana", "pincode": 135021, "available": 3}, {"name": "Kot PHC New", "district": "Yamunanagar", "state": "Haryana", "pincode": 135103, "available": 49}, {"name": "Mandkheri Sub Center", "district": "Yamunanagar", "state": "Haryana", "pincode": 135103, "available": 1}, {"name": "Malikpur Khadar", "district": "Yamunanagar", "state": "Haryana", "pincode": 135106, "available": 18}, {"name": "BAKKARWALA SUB CENTER", "district": "Yamunanagar", "state": "Haryana", "pincode": 135021, "available": 14}]}, {"name": "Himachal Pradesh", "count": 0, "centers": []}, {"name": "Jammu and Kashmir", "count": 14, "centers": [{"name": "Chowki Choura 2 For Covaxin", "district": "Jammu", "state": "Jammu and Kashmir", "pincode": 185154, "available": 1}, {"name": "NTPHC SUKRALA", "district": "Kathua", "state": "Jammu and Kashmir", "pincode": 184204, "available": 172}, {"name": "SMC 8 FBSU AIR FORCE", "district": "Pulwama", "state": "Jammu and Kashmir", "pincode": 192301, "available": 50}, {"name": "Boys Middle School Hazratbal", "district": "Srinagar", "state": "Jammu and Kashmir", "pincode": 190006, "available": 1301}, {"name": "G.B Panth Hospital", "district": "Srinagar", "state": "Jammu and Kashmir", "pincode": 190001, "available": 302}, {"name": "Natipora SC 18-44yrs", "district": "Srinagar", "state": "Jammu and Kashmir", "pincode": 190001, "available": 377}, {"name": "Girls Higher Sec Schl Batmalo", "district": "Srinagar", "state": "Jammu and Kashmir", "pincode": 191202, "available": 796}, {"name": "Community Hall Illahi Bagh", "district": "Srinagar", "state": "Jammu and Kashmir", "pincode": 191202, "available": 1017}, {"name": "HEALTH CENTER MISKEENBAGH", "district": "Srinagar", "state": "Jammu and Kashmir", "pincode": 190003, "available": 489}, {"name": "Nishat PHC 18 Years", "district": "Srinagar", "state": "Jammu and Kashmir", "pincode": 191121, "available": 654}, {"name": "MIRINDA PUBLIC SCHOOL CHINKRAL", "district": "Srinagar", "state": "Jammu and Kashmir", "pincode": 190002, "available": 995}, {"name": "SMHS Well Baby Clinic 18-44age", "district": "Srinagar", "state": "Jammu and Kashmir", "pincode": 190010, "available": 1}, {"name": "Station Medicare Centre AF", "district": "Srinagar", "state": "Jammu and Kashmir", "pincode": 190007, "available": 150}, {"name": "State Cancer Institute Soura", "district": "Srinagar", "state": "Jammu and Kashmir", "pincode": 190011, "available": 906}]}, {"name": "Jharkhand", "count": 1, "centers": [{"name": "JP MEMORIAL HOSPITAL", "district": "Hazaribagh", "state": "Jharkhand", "pincode": 825301, "available": 1}]}, {"name": "Karnataka", "count": 2, "centers": [{"name": "Dodwad PHC", "district": "Belgaum", "state": "Karnataka", "pincode": 591104, "available": 23}, {"name": "Kalaburagi District Hospital", "district": "Gulbarga", "state": "Karnataka", "pincode": 585102, "available": 60}]}, {"name": "Kerala", "count": 0, "centers": []}, {"name": "Ladakh", "count": 0, "centers": []}, {"name": "Lakshadweep", "count": 1, "centers": [{"name": "Test CVC 1", "district": "Agatti Island", "state": "Lakshadweep", "pincode": 999991, "available": 49}]}, {"name": "Madhya Pradesh", "count": 0, "centers": []}, {"name": "Maharashtra", "count": 8, "centers": [{"name": "Dondaicha SDH ( 18-44)", "district": "Dhule", "state": "Maharashtra", "pincode": 425408, "available": 591}, {"name": "Koregaon Phc(18 To 44 Years)", "district": "Gadchiroli", "state": "Maharashtra", "pincode": 441207, "available": 341}, {"name": "Armori SDH (18 To 44 Years)", "district": "Gadchiroli", "state": "Maharashtra", "pincode": 441208, "available": 256}, {"name": "KHANAPUR UPHC (18-44)", "district": "Parbhani", "state": "Maharashtra", "pincode": 431401, "available": 1}, {"name": "Rajapur RH (18-44 Yrs)", "district": "Ratnagiri", "state": "Maharashtra", "pincode": 416702, "available": 1}, {"name": "Kumbhari SC ( 18 To 44 Year )", "district": "Solapur", "state": "Maharashtra", "pincode": 413006, "available": 1}, {"name": "Shri Shidhawar Cancer Hospital", "district": "Solapur", "state": "Maharashtra", "pincode": 413003, "available": 61}, {"name": "Midtown Rotary Club UNR 421002", "district": "Thane", "state": "Maharashtra", "pincode": 421002, "available": 1}]}, {"name": "Manipur", "count": 0, "centers": []}, {"name": "Meghalaya", "count": 0, "centers": []}, {"name": "Mizoram", "count": 0, "centers": []}, {"name": "Nagaland", "count": 0, "centers": []}, {"name": "Odisha", "count": 0, "centers": []}, {"name": "Puducherry", "count": 0, "centers": []}, {"name": "Punjab", "count": 1, "centers": [{"name": "Dhanaula CHC", "district": "Barnala", "state": "Punjab", "pincode": 148105, "available": 100}]}, {"name": "Rajasthan", "count": 17, "centers": [{"name": "18-44 PHC KELPURKHERA RENI", "district": "Alwar", "state": "Rajasthan", "pincode": 301409, "available": 1}, {"name": "18GSSS Ronijathan Block Kherli", "district": "Alwar", "state": "Rajasthan", "pincode": 301035, "available": 70}, {"name": "18-44 PHC PADA RENI", "district": "Alwar", "state": "Rajasthan", "pincode": 301409, "available": 7}, {"name": "18 KHONKAR PHC KHERLI", "district": "Alwar", "state": "Rajasthan", "pincode": 301035, "available": 51}, {"name": "18 RAMNAGAR PHC KHERLI", "district": "Alwar", "state": "Rajasthan", "pincode": 321605, "available": 1}, {"name": "18-44 PHC JAMDOLI RENI", "district": "Alwar", "state": "Rajasthan", "pincode": 301409, "available": 12}, {"name": "Swasthya Mandir Ranjeet Nagar", "district": "Bharatpur", "state": "Rajasthan", "pincode": 321001, "available": 109}, {"name": "UPHC Atalbandh", "district": "Bharatpur", "state": "Rajasthan", "pincode": 321001, "available": 85}, {"name": "RBM BSc Nursing New Building", "district": "Bharatpur", "state": "Rajasthan", "pincode": 321001, "available": 11}, {"name": "UPHC Anand Nagar", "district": "Bharatpur", "state": "Rajasthan", "pincode": 321001, "available": 137}, {"name": "UPHC Tilak Nagar", "district": "Bharatpur", "state": "Rajasthan", "pincode": 321001, "available": 27}, {"name": "Railway School", "district": "Bharatpur", "state": "Rajasthan", "pincode": 321001, "available": 93}, {"name": "Sainik Vishram Grah", "district": "Bharatpur", "state": "Rajasthan", "pincode": 321001, "available": 112}, {"name": "SUKET CHC (18-44 Yrs)", "district": "Kota", "state": "Rajasthan", "pincode": 326530, "available": 81}, {"name": "DESURI- CHC", "district": "Pali", "state": "Rajasthan", "pincode": 306703, "available": 207}, {"name": "NADOL CHC BOOTH-1", "district": "Pali", "state": "Rajasthan", "pincode": 306603, "available": 242}, {"name": "Kotra CHC", "district": "Udaipur", "state": "Rajasthan", "pincode": 307025, "available": 26}]}, {"name": "Sikkim", "count": 0, "centers": []}, {"name": "Tamil Nadu", "count": 1, "centers": [{"name": "Sangeetha SS Hospitals CVC", "district": "Coimbatore", "state": "Tamil Nadu", "pincode": 641008, "available": 100}]}, {"name": "Telangana", "count": 0, "centers": []}, {"name": "Tripura", "count": 0, "centers": []}, {"name": "Uttar Pradesh", "count": 17, "centers": [{"name": "PHC Lohda 5 April", "district": "Chitrakoot", "state": "Uttar Pradesh", "pincode": 210206, "available": 119}, {"name": "PHC Ganeewa 5 April", "district": "Chitrakoot", "state": "Uttar Pradesh", "pincode": 210206, "available": 120}, {"name": "PHC Darseda 5 April", "district": "Chitrakoot", "state": "Uttar Pradesh", "pincode": 210206, "available": 120}, {"name": "PHC Sardhua 5 April", "district": "Chitrakoot", "state": "Uttar Pradesh", "pincode": 210206, "available": 60}, {"name": "CHC Pahari Covishield", "district": "Chitrakoot", "state": "Uttar Pradesh", "pincode": 210206, "available": 204}, {"name": "PHC Bachharan 5 April", "district": "Chitrakoot", "state": "Uttar Pradesh", "pincode": 210206, "available": 119}, {"name": "PHC Bihrawa 5 April", "district": "Chitrakoot", "state": "Uttar Pradesh", "pincode": 210206, "available": 120}, {"name": "CHC Pahari Covaxin", "district": "Chitrakoot", "state": "Uttar Pradesh", "pincode": 210206, "available": 90}, {"name": "PHC Dewal 5 April", "district": "Chitrakoot", "state": "Uttar Pradesh", "pincode": 210206, "available": 120}, {"name": "MAX MULTISPECIALITY CENTRE", "district": "Gautam Buddha Nagar", "state": "Uttar Pradesh", "pincode": 201301, "available": 1}, {"name": "APHC NEWAIJPAR", "district": "Gorakhpur", "state": "Uttar Pradesh", "pincode": 273408, "available": 1}, {"name": "SMC 24 ED AFS", "district": "Prayagraj", "state": "Uttar Pradesh", "pincode": 211012, "available": 2}, {"name": "MLN Medical College1 18 To 44", "district": "Prayagraj", "state": "Uttar Pradesh", "pincode": 211003, "available": 214}, {"name": "PHC JHUNSI 18-44", "district": "Prayagraj", "state": "Uttar Pradesh", "pincode": 221505, "available": 26}, {"name": "CHC KOTWA AT BANI 18-44", "district": "Prayagraj", "state": "Uttar Pradesh", "pincode": 221505, "available": 323}, {"name": "MDI HOSPITAL 18 To 44 Session", "district": "Prayagraj", "state": "Uttar Pradesh", "pincode": 211003, "available": 96}, {"name": "CHC Jasra 18-44", "district": "Prayagraj", "state": "Uttar Pradesh", "pincode": 212107, "available": 506}]}, {"name": "Uttarakhand", "count": 0, "centers": []}, {"name": "West Bengal", "count": 0, "centers": []}]}